django_env_robots/__init__.py
django_env_robots/apps.py
django_env_robots/models.py
django_env_robots/tests.py
django_env_robots/urls.py
django_env_robots/views.py
django_env_robots/templates/robots/default.txt
django_env_robots-0.0.5.dist-info/LICENSE
django_env_robots-0.0.5.dist-info/METADATA
django_env_robots-0.0.5.dist-info/WHEEL
django_env_robots-0.0.5.dist-info/top_level.txt
django_env_robots-0.0.5.dist-info/RECORD
