Metadata-Version: 2.1
Name: django-env-robots
Version: 0.0.5
Summary: Control robots.txt files from environment variables and templates.
Author-email: Pat Smith <pat.smith@cursive.works>
License: MIT License
Project-URL: Homepage, https://github.com/cursive-works/django-env-robots
Keywords: django,robots.txt,environment
Classifier: License :: OSI Approved :: MIT License
Classifier: Programming Language :: Python
Classifier: Programming Language :: Python :: 3
Requires-Python: >=3.9
License-File: LICENSE
Requires-Dist: django >=3.2
